{
  "url": "https://flexpay.io/news/deloitte-2019-companies/",
  "filename": "063_news_deloitte-2019-companies_.md",
  "title": "FlexPay Wins Deloitte Award",
  "summary": "FlexPay has been recognized as a Companies-to-Watch 2019 winner by Deloitte, highlighting its rapid revenue growth and commitment to innovation. The award acknowledges Canadian technology companies that have demonstrated significant achievements between 2015 and 2018. The article also touches on the growing adoption of AI and cognitive technologies among these fast-growing companies.",
  "content_type": "other",
  "importance_score": 7,
  "key_points": [
    "FlexPay is a Deloitte Companies-to-Watch 2019 award winner.",
    "The award recognizes innovation, leadership, and rapid revenue growth.",
    "Canadian technology companies are increasingly adopting AI and cognitive technologies.",
    "Advancements in technology are seen as both a challenge and an opportunity for growth."
  ]
}