{
  "url": "https://flexpay.io/blog/the-future-of-shopping-how-gen-z-has-embraced-subscriptions/",
  "filename": "183_blog_the-future-of-shopping-ho.md",
  "title": "The Future of Shopping: How Gen Z Has Embraced Subscriptions",
  "summary": "This article explores how Generation Z, as digital natives, are driving the growth of subscription businesses. Their heavy reliance on smartphones and online platforms for shopping makes them a key demographic for subscription services, from streaming to fashion and electronics.",
  "content_type": "other",
  "importance_score": 7,
  "key_points": [
    "Gen Z are digital natives who shop extensively via smartphones.",
    "The pandemic accelerated e-commerce adoption across all age groups.",
    "Gen Z discovers and purchases products through social media.",
    "Subscription models are appealing to Gen Z for various product categories."
  ]
}